apiverve_randomidentity/__init__.py
apiverve_randomidentity/apiClient.py
apiverve_randomidentity/exceptions.py
apiverve_randomidentity/setup.py
apiverve_randomidentity/tests/__init__.py
apiverve_randomidentity/tests/test_api.py
apiverve_randomidentity-1.0.11.dist-info/LICENSE
apiverve_randomidentity-1.0.11.dist-info/METADATA
apiverve_randomidentity-1.0.11.dist-info/WHEEL
apiverve_randomidentity-1.0.11.dist-info/top_level.txt
apiverve_randomidentity-1.0.11.dist-info/RECORD
